travis_wait_improved/__init__.py
travis_wait_improved/_version.py
travis_wait_improved/sherpa.py
travis_wait_improved-1.0.0.dist-info/LICENSE
travis_wait_improved-1.0.0.dist-info/METADATA
travis_wait_improved-1.0.0.dist-info/WHEEL
travis_wait_improved-1.0.0.dist-info/entry_points.txt
travis_wait_improved-1.0.0.dist-info/top_level.txt
travis_wait_improved-1.0.0.dist-info/RECORD
