Metadata-Version: 2.1
Name: travis-wait-improved
Version: 1.0.0
Summary: A tool to help long-running, yet reticent, processes avoid death at the hands of Traivs-CI.
Home-page: https://www.us-cert.gov/resources/ncats
Author: Cyber and Infrastructure Security Agency
Author-email: ncats@hq.dhs.gov
License: License :: CC0 1.0 Universal (CC0 1.0) Public Domain Dedication
Download-URL: https://github.com/cisagov/travis-wait-improved
Keywords: travis-wait travis-ci sherpa travis_wait
Platform: UNKNOWN
Classifier: Development Status :: 5 - Production/Stable
Classifier: Intended Audience :: Developers
Classifier: License :: CC0 1.0 Universal (CC0 1.0) Public Domain Dedication
Classifier: Programming Language :: Python :: 3
Classifier: Programming Language :: Python :: 3.6
Classifier: Programming Language :: Python :: 3.7
Classifier: Programming Language :: Python :: 3.8
Requires-Python: >=3.6
Requires-Dist: docopt
Requires-Dist: termcolor
Provides-Extra: test
Requires-Dist: pre-commit ; extra == 'test'
Requires-Dist: coveralls ; extra == 'test'
Requires-Dist: coverage (<5.0) ; extra == 'test'
Requires-Dist: pytest-cov ; extra == 'test'
Requires-Dist: pytest ; extra == 'test'
